adafruit_vl6180x.py
adafruit_circuitpython_vl6180x-1.4.19.dist-info/licenses/LICENSE
adafruit_circuitpython_vl6180x-1.4.19.dist-info/METADATA
adafruit_circuitpython_vl6180x-1.4.19.dist-info/WHEEL
adafruit_circuitpython_vl6180x-1.4.19.dist-info/top_level.txt
adafruit_circuitpython_vl6180x-1.4.19.dist-info/RECORD
